moitoi_docker_hive/__init__.py
moitoi_docker_hive/cli.py
moitoi_docker_hive/main.py
moitoi_docker_hive/assets/__init__.py
moitoi_docker_hive/assets/backend/Dockerfile
moitoi_docker_hive/assets/backend/__init__.py
moitoi_docker_hive/assets/backend/app.py
moitoi_docker_hive/assets/backend/config.py
moitoi_docker_hive/assets/backend/forms.py
moitoi_docker_hive/assets/backend/requirements.txt
moitoi_docker_hive/assets/backend/start.sh
moitoi_docker_hive/assets/backend/start_gunicorn.sh
moitoi_docker_hive/assets/backend/start_telegraf.sh
moitoi_docker_hive/assets/backend/telegraf.conf
moitoi_docker_hive/assets/backend/static/script.js
moitoi_docker_hive/assets/backend/templates/index.html
moitoi_docker_hive/assets/base/Dockerfile
moitoi_docker_hive/assets/base/start.sh
moitoi_docker_hive/assets/base/start_telegraf.sh
moitoi_docker_hive/assets/base/telegraf.conf
moitoi_docker_hive/assets/elsa/Dockerfile
moitoi_docker_hive/assets/elsa/__init__.py
moitoi_docker_hive/assets/elsa/app.py
moitoi_docker_hive/assets/elsa/requirements.txt
moitoi_docker_hive/assets/elsa/start.sh
moitoi_docker_hive/assets/elsa/start_gunicorn.sh
moitoi_docker_hive/assets/elsa/start_telegraf.sh
moitoi_docker_hive/assets/elsa/telegraf.conf
moitoi_docker_hive/assets/elsa/wd.py
moitoi_docker_hive/assets/elsa/rest/__init__.py
moitoi_docker_hive/assets/elsa/rest/controller.py
moitoi_docker_hive/assets/elsa/rest/main.py
moitoi_docker_hive/assets/elsa/rest/models.py
moitoi_docker_hive/assets/elsa/worker/__init__.py
moitoi_docker_hive/assets/elsa/worker/main.py
moitoi_docker_hive/assets/elsa/worker/models.py
moitoi_docker_hive/assets/grafana/Dockerfile
moitoi_docker_hive/assets/grafana/dashboard.json
moitoi_docker_hive/assets/grafana/dashboard.yml
moitoi_docker_hive/assets/grafana/datasource.yml
moitoi_docker_hive/assets/grafana/grafana.ini
moitoi_docker_hive/assets/lb/502.html
moitoi_docker_hive/assets/lb/Dockerfile
moitoi_docker_hive/assets/lb/nginx.conf
moitoi_docker_hive/assets/lb/start.sh
moitoi_docker_hive-0.1.10.dist-info/AUTHORS.rst
moitoi_docker_hive-0.1.10.dist-info/LICENSE
moitoi_docker_hive-0.1.10.dist-info/METADATA
moitoi_docker_hive-0.1.10.dist-info/WHEEL
moitoi_docker_hive-0.1.10.dist-info/entry_points.txt
moitoi_docker_hive-0.1.10.dist-info/top_level.txt
moitoi_docker_hive-0.1.10.dist-info/RECORD
