Metadata-Version: 2.1
Name: moitoi-docker-hive
Version: 0.1.10
Summary: MoiToi Docker Hive is simple dockrized containers manager
Home-page: https://github.com/kepsic/moitoi_docker_hive
Author: Andres Kepler
Author-email: andres@kepler.ee
License: MIT license
Keywords: moitoi_docker_hive
Platform: UNKNOWN
Classifier: Development Status :: 2 - Pre-Alpha
Classifier: Intended Audience :: Developers
Classifier: License :: OSI Approved :: MIT License
Classifier: Natural Language :: English
Classifier: Programming Language :: Python :: 3.6
Classifier: Programming Language :: Python :: 3.7
Classifier: Programming Language :: Python :: 3.8
Requires-Python: >=3.6
Requires-Dist: docker
Requires-Dist: paramiko
Requires-Dist: flask
Requires-Dist: flask-restful
Requires-Dist: pyyaml
